README
README.md
setup.py
sheetsite/__init__.py
sheetsite/chain.py
sheetsite/cmdline.py
sheetsite/csv_spreadsheet.py
sheetsite/expand.py
sheetsite/filtered_spreadsheet.py
sheetsite/geocache.py
sheetsite/google_spreadsheet.py
sheetsite/ids.py
sheetsite/json_spreadsheet.py
sheetsite/jsonify.py
sheetsite/merged_spreadsheet.py
sheetsite/names.py
sheetsite/sheetsend.py
sheetsite/sheetwatch.py
sheetsite/site.py
sheetsite/site_queue.py
sheetsite/spreadsheet.py
sheetsite/xls_spreadsheet.py
sheetsite.egg-info/PKG-INFO
sheetsite.egg-info/SOURCES.txt
sheetsite.egg-info/dependency_links.txt
sheetsite.egg-info/entry_points.txt
sheetsite.egg-info/requires.txt
sheetsite.egg-info/top_level.txt
sheetsite/destination/__init__.py
sheetsite/destination/csv_ss.py
sheetsite/destination/drop.py
sheetsite/destination/excel.py
sheetsite/destination/ftp.py
sheetsite/destination/git.py
sheetsite/destination/install_local_soup.py
sheetsite/destination/json_ss.py
sheetsite/destination/sqlite_ss.py
sheetsite/destination/stone_soup.py
sheetsite/destination/stone_soup_v2.py
sheetsite/source/__init__.py
sheetsite/source/csv.py
sheetsite/source/excel.py
sheetsite/source/google.py
sheetsite/source/json.py
sheetsite/tasks/__init__.py
sheetsite/tasks/detect_site.py
sheetsite/tasks/notify.py
sheetsite/tasks/update_site.py
sheetsite/tweaks/__init__.py
sheetsite/tweaks/add_dccid.py
sheetsite/tweaks/coalesce.py
sheetsite/tweaks/formula.py
sheetsite/tweaks/list_to_rows.py
sheetsite/tweaks/merge_tables.py
sheetsite/tweaks/patch.py
sheetsite/tweaks/prune_tables.py
sheetsite/tweaks/rename_column.py
sheetsite/tweaks/rename_table.py
sheetsite/tweaks/replace_cell.py
sheetsite/tweaks/required_field.py
sheetsite/tweaks/sniff_inactive.py
sheetsite/tweaks/split_addresses.py
sheetsite/tweaks/split_addresses_v2.py
sheetsite/tweaks/us_state.py
sheetsite/tweaks/us_zip.py