Metadata-Version: 1.1
Name: sheetsite
Version: 0.2.2
Summary: read google sheets, use them for sites
Home-page: https://github.com/paulfitz/sheetsite
Author: Paul Fitzpatrick
Author-email: paul.michael.fitzpatrick@gmail.com
License: MIT
Keywords: google sheet xls json
Platform: UNKNOWN
Classifier: Development Status :: 3 - Alpha
Classifier: Topic :: Utilities
Classifier: License :: OSI Approved :: MIT License
